_pyminmax.cpython-312-darwin.so
pyminmax/__init__.py
pyminmax/_pyminmaxmodule.c
pyminmax/tests/__init__.py
pyminmax/tests/__main__.py
pyminmax/tests/test_minmax.py
pyminmax-0.1.5.dist-info/licenses/LICENSE
pyminmax-0.1.5.dist-info/METADATA
pyminmax-0.1.5.dist-info/WHEEL
pyminmax-0.1.5.dist-info/top_level.txt
pyminmax-0.1.5.dist-info/RECORD
