Metadata-Version: 2.4
Name: pyminmax
Version: 0.1.5
Summary: minmax(x): min(x), max(x) in one pass
Author: Owain Davies
License: MIT License
Project-URL: homepage, https://github.com/OTheDev/pyminmax
Classifier: Programming Language :: Python :: 3
Classifier: License :: OSI Approved :: MIT License
Classifier: Operating System :: OS Independent
Classifier: Intended Audience :: Developers
Requires-Python: >=3.10.1
License-File: LICENSE
Dynamic: license-file
